{
  "metadata": {
    "record_id": "1944.100.50144",
    "coin_page_url": "https://numismatics.org/collection/1944.100.50144",
    "title": "Silver Denarius of Septimius Severus, Rome, 196–197. 1944.100.50144",
    "date_range": {
      "from": "0196",
      "to": "0197"
    },
    "obverse_portrait": "Septimius Severus",
    "material": "http://nomisma.org/id/ar",
    "denomination": "http://nomisma.org/id/denarius",
    "cat": "RIC IV Septimius Severus 86 (denarius)",
    "Obverse_leg": "L SEPT SEV PERT AVG IMP VIII",
    "rev_symbol": null,
    "measurements": {
      "weight": "3.05 g",
      "diameter": "17.2 mm"
    },
    "descriptions": {
      "obverse": "Head of Septimius Severus, laureate, right",
      "reverse": "Victory, advancing left, holding wreath in right and palm in left"
    }
  },
  "images": {
    "obverse": [
      {
        "type": "iiif",
        "url": "https://images.numismatics.org/collectionimages/19001949/1944/1944.100.50144.obv.noscale.jpg"
      },
      {
        "type": "archive",
        "url": "https://numismatics.org/collectionimages/19001949/1944/1944.100.50144.obv.noscale.jpg"
      },
      {
        "type": "reference",
        "url": "https://numismatics.org/collectionimages/19001949/1944/1944.100.50144.obv.width350.jpg"
      },
      {
        "type": "thumbnail",
        "url": "https://numismatics.org/collectionimages/19001949/1944/1944.100.50144.obv.width175.jpg"
      }
    ],
    "reverse": [
      {
        "type": "iiif",
        "url": "https://images.numismatics.org/collectionimages/19001949/1944/1944.100.50144.rev.noscale.jpg"
      },
      {
        "type": "archive",
        "url": "https://numismatics.org/collectionimages/19001949/1944/1944.100.50144.rev.noscale.jpg"
      },
      {
        "type": "reference",
        "url": "https://numismatics.org/collectionimages/19001949/1944/1944.100.50144.rev.width350.jpg"
      },
      {
        "type": "thumbnail",
        "url": "https://numismatics.org/collectionimages/19001949/1944/1944.100.50144.rev.width175.jpg"
      }
    ]
  }
}