<?xml version="1.0" encoding="UTF-8"?><nuds xmlns="http://nomisma.org/nuds" xmlns:mets="http://www.loc.gov/METS/" xmlns:tei="http://www.tei-c.org/ns/1.0" xmlns:xs="http://www.w3.org/2001/XMLSchema" xmlns:xlink="http://www.w3.org/1999/xlink" recordType="physical">
  <control>
    <recordId>0000.999.32529</recordId>
    <publicationStatus>approved</publicationStatus>
    <maintenanceStatus>new</maintenanceStatus>
    <maintenanceAgency>
      <agencyName>American Numismatic Society</agencyName>
    </maintenanceAgency>
    <maintenanceHistory>
      <maintenanceEvent>
        <eventType>derived</eventType>
        <eventDateTime standardDateTime="2024-05-15T11:05:56Z">May 15 2024 at 11:05:56</eventDateTime>
        <agentType>machine</agentType>
        <agent>PHP</agent>
      </maintenanceEvent>
    </maintenanceHistory>
    <rightsStmt>
      <copyrightHolder>American Numismatic Society</copyrightHolder>
      <license for="data" xlink:type="simple" xlink:href="http://opendatacommons.org/licenses/odbl/">Metadata are openly licensed with a Open Data Commons Open Database License (OdbL)</license>
      <license for="images" xlink:type="simple" xlink:href="https://creativecommons.org/choose/mark/">Public Domain Mark</license>
      <rights xlink:type="simple" xlink:href="http://rightsstatements.org/vocab/NoC-US/1.0/">No Copyright - United States</rights>
    </rightsStmt>
    <semanticDeclaration>
      <prefix>nmo</prefix>
      <namespace>http://nomisma.org/ontology#</namespace>
    </semanticDeclaration>
  </control>
  <descMeta>
    <title xml:lang="en">Bronze Medallion of Marcus Aurelius, 161–180. 0000.999.32529</title>
    <subjectSet>
      <subject xml:id="f319885b-5d75-3ad8-a9e9-6709324f6507--a48923a8-9322-3bd0-b530-a3b6563d20eb--31924f54-4830-312d-aae8-2d774cbc0133" localType="category">Roman--Modern--Copy</subject>
    </subjectSet>
    <typeDesc>
      <objectType xlink:type="simple">Medallion</objectType>
      <dateRange>
        <fromDate standardDate="0161">161</fromDate>
        <nuds:toDate xmlns:nuds="http://nomisma.org/nuds" standardDate="0180">180</nuds:toDate>
      </dateRange>
      <manufacture xlink:href="http://nomisma.org/id/struck" xlink:type="simple">Struck</manufacture>
      <material xlink:href="http://nomisma.org/id/ae" xlink:type="simple">Bronze</material>
      <authority>
        <persname xlink:role="authority" xlink:href="http://nomisma.org/id/marcus_aurelius" xlink:type="simple">Marcus Aurelius</persname>
        <corpname xlink:role="state" xlink:href="http://nomisma.org/id/roman_empire" xlink:type="simple">Roman Empire</corpname>
      </authority>
      <obverse>
        <legend>M ANTONINVS AVG TR P XXIX</legend>
        <nuds:type xmlns:nuds="http://nomisma.org/nuds">
          <description xml:lang="en">Head laur. r.</description>
        </nuds:type>
        <persname xlink:href="http://nomisma.org/id/marcus_aurelius" xlink:role="portrait" xlink:type="simple">Marcus Aurelius</persname>
      </obverse>
      <reverse>
        <legend>IMP VII COS III</legend>
        <nuds:type xmlns:nuds="http://nomisma.org/nuds">
          <description xml:lang="en">Victory sitting r. w/ trophy</description>
        </nuds:type>
      </reverse>
    </typeDesc>
    <physDesc>
      <axis>12</axis>
      <measurementsSet>
        <weight units="g">28.84</weight>
        <diameter units="mm">35</diameter>
      </measurementsSet>
    </physDesc>
    <adminDesc>
      <nuds:identifier xmlns:nuds="http://nomisma.org/nuds">0000.999.32529</nuds:identifier>
      <lot>0000.999</lot>
      <department>Roman</department>
      <collection xlink:href="http://nomisma.org/id/ans" xlink:type="simple">American Numismatic Society</collection>
    </adminDesc>
  </descMeta>
  <digRep>
    <mets:fileSec>
        <mets:fileGrp USE="obverse">
            <mets:file USE="iiif">
                <mets:FLocat LOCYPE="URL" xlink:href="https://images.numismatics.org/collectionimages%2F00001899%2F0000%2F0000.999.32529.obv.noscale.jpg"/>
            </mets:file>
            <mets:file USE="archive" MIMETYPE="image/jpeg">
                <mets:FLocat LOCYPE="URL" xlink:href="https://numismatics.org/collectionimages/00001899/0000/0000.999.32529.obv.noscale.jpg"/>
            </mets:file>
            <mets:file USE="reference" MIMETYPE="image/jpeg">
                <mets:FLocat LOCYPE="URL" xlink:href="https://numismatics.org/collectionimages/00001899/0000/0000.999.32529.obv.width350.jpg"/>
            </mets:file>
            <mets:file USE="thumbnail" MIMETYPE="image/jpeg">
                <mets:FLocat LOCYPE="URL" xlink:href="https://numismatics.org/collectionimages/00001899/0000/0000.999.32529.obv.width175.jpg"/>
            </mets:file>
        </mets:fileGrp>
        <mets:fileGrp USE="reverse">
            <mets:file USE="iiif">
                <mets:FLocat LOCYPE="URL" xlink:href="https://images.numismatics.org/collectionimages%2F00001899%2F0000%2F0000.999.32529.rev.noscale.jpg"/>
            </mets:file>
            <mets:file USE="archive" MIMETYPE="image/jpeg">
                <mets:FLocat LOCYPE="URL" xlink:href="https://numismatics.org/collectionimages/00001899/0000/0000.999.32529.rev.noscale.jpg"/>
            </mets:file>
            <mets:file USE="reference" MIMETYPE="image/jpeg">
                <mets:FLocat LOCYPE="URL" xlink:href="https://numismatics.org/collectionimages/00001899/0000/0000.999.32529.rev.width350.jpg"/>
            </mets:file>
            <mets:file USE="thumbnail" MIMETYPE="image/jpeg">
                <mets:FLocat LOCYPE="URL" xlink:href="https://numismatics.org/collectionimages/00001899/0000/0000.999.32529.rev.width175.jpg"/>
            </mets:file>
        </mets:fileGrp>
    </mets:fileSec>
</digRep>
</nuds>